collibra_importer/__init__.py
collibra_importer/api_client.py
collibra_importer/configuration.py
collibra_importer/exceptions.py
collibra_importer/rest.py
collibra_importer/api/__init__.py
collibra_importer/api/import_api.py
collibra_importer/api/import_results_api.py
collibra_importer/models/__init__.py
collibra_importer/models/asset_identifier.py
collibra_importer/models/asset_import_command.py
collibra_importer/models/asset_type_identifier.py
collibra_importer/models/attribute_value.py
collibra_importer/models/category_reference.py
collibra_importer/models/community_identifier.py
collibra_importer/models/community_import_command.py
collibra_importer/models/complex_relation_identifier.py
collibra_importer/models/complex_relation_import_command.py
collibra_importer/models/complex_relation_type_identifier.py
collibra_importer/models/domain_identifier.py
collibra_importer/models/domain_import_command.py
collibra_importer/models/domain_type_identifier.py
collibra_importer/models/external_identifier.py
collibra_importer/models/find_synchronization_request.py
collibra_importer/models/import_command_reference.py
collibra_importer/models/import_counters.py
collibra_importer/models/import_csv_in_job_request.py
collibra_importer/models/import_error.py
collibra_importer/models/import_error_paged_response.py
collibra_importer/models/import_excel_in_job_request.py
collibra_importer/models/import_json_in_job_request.py
collibra_importer/models/import_summary.py
collibra_importer/models/inline_object.py
collibra_importer/models/inline_object1.py
collibra_importer/models/inline_object2.py
collibra_importer/models/inline_object3.py
collibra_importer/models/inline_object4.py
collibra_importer/models/inline_object5.py
collibra_importer/models/inline_object6.py
collibra_importer/models/inline_object7.py
collibra_importer/models/inline_object8.py
collibra_importer/models/inline_object9.py
collibra_importer/models/job.py
collibra_importer/models/mapping_identifier.py
collibra_importer-2.0.0.post6.dist-info/METADATA
collibra_importer-2.0.0.post6.dist-info/WHEEL
collibra_importer-2.0.0.post6.dist-info/top_level.txt
collibra_importer-2.0.0.post6.dist-info/RECORD
